{"Valgart":"Kommunal- og regionsrådsvalg","Valgdag":"18-11-2025","FrigivelsesTidspunktUTC":"18-11-2025 17:02:44","Kommune":"Ringkøbing-Skjern","Kommunekode":760,"Afstemningsområde":"Holmsland","AfstemningsområdeDagiId":"706404","AfstemningsområdeNummer":2,"Valgdeltagelse":[{"AntalStemmeberretigedeVælgere":1040,"AfgivneStemmer":167,"Tidspunkt":"11:00:00"},{"AntalStemmeberretigedeVælgere":1040,"AfgivneStemmer":249,"Tidspunkt":"12:00:00"},{"AntalStemmeberretigedeVælgere":1040,"AfgivneStemmer":294,"Tidspunkt":"13:00:00"},{"AntalStemmeberretigedeVælgere":1040,"AfgivneStemmer":330,"Tidspunkt":"14:00:00"},{"AntalStemmeberretigedeVælgere":1040,"AfgivneStemmer":384,"Tidspunkt":"15:00:00"},{"AntalStemmeberretigedeVælgere":1040,"AfgivneStemmer":465,"Tidspunkt":"16:00:00"},{"AntalStemmeberretigedeVælgere":1040,"AfgivneStemmer":570,"Tidspunkt":"17:00:00"},{"AntalStemmeberretigedeVælgere":1040,"AfgivneStemmer":692,"Tidspunkt":"18:00:00"}]}