{"Kandidatlister":[{"KandidatlisteId":"739142e9-bd36-4be7-9d1e-147d7a75ec5f","Navn":"Socialdemokratiet","Bogstavbetegnelse":"A","Stemmer":1172,"Listestemmer":null,"StemmerDifferenceFraForrigeValg":-529,"Kandidater":null},{"KandidatlisteId":"9ae8c0c7-94aa-445a-aa71-5ebb90b5935e","Navn":"Alternativet","Bogstavbetegnelse":"Å","Stemmer":43,"Listestemmer":null,"StemmerDifferenceFraForrigeValg":-49,"Kandidater":null},{"KandidatlisteId":"febdae01-6cf5-485c-aee7-822a4144043d","Navn":"Furesørødderne","Bogstavbetegnelse":"E","Stemmer":190,"Listestemmer":null,"StemmerDifferenceFraForrigeValg":null,"Kandidater":null},{"KandidatlisteId":"c6aafe76-1b92-4361-8e66-de165b3509ea","Navn":"Socialistisk Folkeparti","Bogstavbetegnelse":"F","Stemmer":393,"Listestemmer":null,"StemmerDifferenceFraForrigeValg":null,"Kandidater":null},{"KandidatlisteId":"9de1c019-4c36-49e0-b205-5f97706ee8ec","Navn":"Venstre Danmarks Liberale Parti","Bogstavbetegnelse":"V","Stemmer":737,"Listestemmer":null,"StemmerDifferenceFraForrigeValg":null,"Kandidater":null},{"KandidatlisteId":"179f5dfe-2f8c-4167-98b5-5be9cfcb29eb","Navn":"Enhedslisten - De Rød-Grønne","Bogstavbetegnelse":"Ø","Stemmer":438,"Listestemmer":null,"StemmerDifferenceFraForrigeValg":35,"Kandidater":null},{"KandidatlisteId":"546dba06-8ab9-405b-8ea6-a16d6a42a53b","Navn":"Radikale Venstre","Bogstavbetegnelse":"B","Stemmer":689,"Listestemmer":null,"StemmerDifferenceFraForrigeValg":229,"Kandidater":null},{"KandidatlisteId":"e1f9984a-9fd9-492e-925b-082679e131cb","Navn":"Det Konservative Folkeparti","Bogstavbetegnelse":"C","Stemmer":1163,"Listestemmer":null,"StemmerDifferenceFraForrigeValg":32,"Kandidater":null},{"KandidatlisteId":"b9d51679-0517-42fe-a8f0-7714de662306","Navn":"Moderaterne","Bogstavbetegnelse":"M","Stemmer":39,"Listestemmer":null,"StemmerDifferenceFraForrigeValg":null,"Kandidater":null},{"KandidatlisteId":"248364d6-1fd4-4bce-bb76-853546c64a52","Navn":"Liberal Alliance","Bogstavbetegnelse":"I","Stemmer":296,"Listestemmer":null,"StemmerDifferenceFraForrigeValg":158,"Kandidater":null},{"KandidatlisteId":"8ddace1d-02e4-4d2f-8288-78fe232864c0","Navn":"Lokallisten Bedre Borgerinddragelse","Bogstavbetegnelse":"L","Stemmer":10,"Listestemmer":null,"StemmerDifferenceFraForrigeValg":null,"Kandidater":null},{"KandidatlisteId":"f482dd64-4203-491b-9e4c-2d084b43bbbe","Navn":"Dansk Folkeparti","Bogstavbetegnelse":"O","Stemmer":129,"Listestemmer":null,"StemmerDifferenceFraForrigeValg":66,"Kandidater":null}],"GodkendelsesDatoUTC":"18-11-2025 22:32:01","Valgdag":"18-11-2025","Valgart":"Kommunalvalg","FrigivelsesTidspunktUTC":"18-11-2025 22:52:39","Storkreds":null,"Storkredsnummer":null,"Opstillingskreds":null,"OpstillingskredsDagiId":null,"Kommune":"Furesø","Kommunekode":190,"AfstemningsområdeNummer":6,"AfstemningsområdeDagiId":705614,"Afstemningsområde":"Solvang","UgyldigeFremmødteStemmerÅrsager":[{"Id":1,"Navn":"Blanke","Paragraf":"4","Antal":56}],"UgyldigeBrevstemmerÅrsager":[{"Id":21,"Navn":"Blanke","Paragraf":"19","Antal":16}],"Resultatart":"ForeløbigOptælling","AfgivneStemmer":5386,"GyldigeStemmer":5299,"UgyldigeStemmerUdoverBlanke":15,"BlankeUgyldigeFremmødteStemmer":56,"BlankeUgyldigeBrevstemmer":16,"AfgivneStemmerDifferenceFraForrigeValg":358,"GyldigeStemmerDifferenceFraForrigeValg":318,"UgyldigeStemmerDifferenceFraForrigeValg":5,"BlankeStemmerDifferenceFraForrigeValg":35,"AntalStemmeberettigedeVælgereDifferenceFraForrigeValg":238,"AntalStemmeberettigedeVælgere":6873}