{"Kandidatlister":[{"KandidatlisteId":"bd54468b-e6d3-47a5-b010-959da4016bde","Navn":"Radikale Venstre","Bogstavbetegnelse":"B","Stemmer":19,"Listestemmer":null,"StemmerDifferenceFraForrigeValg":12,"Kandidater":null},{"KandidatlisteId":"eb0d0cfa-11f0-4aa2-bdcb-bec302bf5975","Navn":"Socialdemokratiet","Bogstavbetegnelse":"A","Stemmer":103,"Listestemmer":null,"StemmerDifferenceFraForrigeValg":-67,"Kandidater":null},{"KandidatlisteId":"d1b534a5-e90b-4795-941b-b221dbc406c7","Navn":"Nordfyn på forkant","Bogstavbetegnelse":"E","Stemmer":7,"Listestemmer":null,"StemmerDifferenceFraForrigeValg":null,"Kandidater":null},{"KandidatlisteId":"2f35b336-ac94-4eb2-aac5-5cadac79564f","Navn":"Danmarksdemokraterne","Bogstavbetegnelse":"Æ","Stemmer":106,"Listestemmer":null,"StemmerDifferenceFraForrigeValg":null,"Kandidater":null},{"KandidatlisteId":"54262950-ba64-4116-b728-c73ec4ec2793","Navn":"Enhedslisten","Bogstavbetegnelse":"Ø","Stemmer":10,"Listestemmer":null,"StemmerDifferenceFraForrigeValg":null,"Kandidater":null},{"KandidatlisteId":"c35d32c7-57d9-4d43-8110-6c0af6f692f5","Navn":"Det Konservative Folkeparti","Bogstavbetegnelse":"C","Stemmer":23,"Listestemmer":null,"StemmerDifferenceFraForrigeValg":-4,"Kandidater":null},{"KandidatlisteId":"1ac1e821-605b-42d9-b0ab-2f182eee716c","Navn":"Vi ældre","Bogstavbetegnelse":"D","Stemmer":4,"Listestemmer":null,"StemmerDifferenceFraForrigeValg":null,"Kandidater":null},{"KandidatlisteId":"f4cb0510-0d5b-4668-b713-8dcb0b410d94","Navn":"Socialistisk Folkeparti - SF","Bogstavbetegnelse":"F","Stemmer":57,"Listestemmer":null,"StemmerDifferenceFraForrigeValg":null,"Kandidater":null},{"KandidatlisteId":"ad7ce3b0-1fda-46f0-b950-fb2f6ec7fec3","Navn":"Liberal Alliance","Bogstavbetegnelse":"I","Stemmer":35,"Listestemmer":null,"StemmerDifferenceFraForrigeValg":null,"Kandidater":null},{"KandidatlisteId":"97c56709-4fb3-43d5-baf6-49092b80635a","Navn":"Dansk Folkeparti","Bogstavbetegnelse":"O","Stemmer":42,"Listestemmer":null,"StemmerDifferenceFraForrigeValg":-35,"Kandidater":null},{"KandidatlisteId":"156a5ef5-343f-47a5-b0a7-f4b4e3382403","Navn":"Venstre","Bogstavbetegnelse":"V","Stemmer":268,"Listestemmer":null,"StemmerDifferenceFraForrigeValg":null,"Kandidater":null}],"GodkendelsesDatoUTC":"18-11-2025 20:08:01","Valgdag":"18-11-2025","Valgart":"Kommunalvalg","FrigivelsesTidspunktUTC":"18-11-2025 20:10:00","Storkreds":null,"Storkredsnummer":null,"Opstillingskreds":null,"OpstillingskredsDagiId":null,"Kommune":"Nordfyns","Kommunekode":480,"AfstemningsområdeNummer":7,"AfstemningsområdeDagiId":748635,"Afstemningsområde":"Hårslev","UgyldigeFremmødteStemmerÅrsager":[{"Id":4,"Navn":"KrydsUdenForFelterne","Paragraf":"7","Antal":1},{"Id":7,"Navn":"OverstregetUdvisketEllerIkkeFuldtKryds","Paragraf":"11","Antal":1},{"Id":1,"Navn":"Blanke","Paragraf":"4","Antal":10},{"Id":3,"Navn":"HeltEllerDelvistOverstreget","Paragraf":"6","Antal":0},{"Id":2,"Navn":"AndetMærkeEndKryds","Paragraf":"5","Antal":0},{"Id":5,"Navn":"KrydsIflereFelter","Paragraf":"8","Antal":0},{"Id":6,"Navn":"KrydsRækkerIndIflereFelter","Paragraf":"9,10","Antal":0},{"Id":9,"Navn":"StemmeseddelIkkeUdFraAfstemningssted","Paragraf":"13","Antal":0},{"Id":8,"Navn":"AndreGrunde","Paragraf":"12","Antal":0},{"Id":10,"Navn":"AndetMærkeEndKrydsForudenKryds","Paragraf":"14","Antal":0},{"Id":13,"Navn":"AfmærketMedForskelligeFarverOgAndet","Paragraf":"17","Antal":0},{"Id":11,"Navn":"AnførtFlereEndTreKryds","Paragraf":"15","Antal":0},{"Id":12,"Navn":"StemmeseddelMedTegningPåskrift","Paragraf":"16","Antal":0}],"UgyldigeBrevstemmerÅrsager":[{"Id":21,"Navn":"Blanke","Paragraf":"19","Antal":0},{"Id":32,"Navn":"UdfyldtPåBagsidenEllerAndet","Paragraf":"31","Antal":0},{"Id":29,"Navn":"StemmeseddelIkkeFraMinisteren","Paragraf":"28","Antal":0},{"Id":30,"Navn":"KonvolutMedPåskrift","Paragraf":"29","Antal":0},{"Id":31,"Navn":"StemmeseddelMedTegningPåskrift","Paragraf":"30","Antal":0},{"Id":22,"Navn":"KunNavnUofficielBogstav","Paragraf":"20","Antal":0},{"Id":23,"Navn":"KunUofficelBogstavPåEtBogstav","Paragraf":"21","Antal":0},{"Id":26,"Navn":"ModstridBogstavListeNavn","Paragraf":"24, 25","Antal":0},{"Id":25,"Navn":"KunKryds","Paragraf":"23","Antal":0},{"Id":28,"Navn":"AndetEllerMereEndEnStemmeseddel","Paragraf":"27","Antal":0},{"Id":27,"Navn":"AndreGrunde","Paragraf":"26","Antal":0},{"Id":24,"Navn":"KunUofficelBogstavPåFlereBogstaver","Paragraf":"22","Antal":0}],"Resultatart":"ForeløbigOptælling","AfgivneStemmer":686,"GyldigeStemmer":674,"UgyldigeStemmerUdoverBlanke":2,"BlankeUgyldigeFremmødteStemmer":10,"BlankeUgyldigeBrevstemmer":0,"AfgivneStemmerDifferenceFraForrigeValg":-6,"GyldigeStemmerDifferenceFraForrigeValg":-5,"UgyldigeStemmerDifferenceFraForrigeValg":1,"BlankeStemmerDifferenceFraForrigeValg":-2,"AntalStemmeberettigedeVælgereDifferenceFraForrigeValg":31,"AntalStemmeberettigedeVælgere":1070}