{"Kandidatlister":[{"KandidatlisteId":"e06b8df3-c2c0-4a01-9eb6-915a59d43dbe","Navn":"Socialdemokratiet","Bogstavbetegnelse":"A","Stemmer":887,"Listestemmer":null,"StemmerDifferenceFraForrigeValg":-270,"Kandidater":null},{"KandidatlisteId":"7130f580-7037-4daf-86df-ec52cd3625e6","Navn":"Det Konservative Folkeparti","Bogstavbetegnelse":"C","Stemmer":225,"Listestemmer":null,"StemmerDifferenceFraForrigeValg":80,"Kandidater":null},{"KandidatlisteId":"95ac7b65-9c55-47b7-9d73-50536aa0aa46","Navn":"Moderaterne","Bogstavbetegnelse":"M","Stemmer":42,"Listestemmer":null,"StemmerDifferenceFraForrigeValg":null,"Kandidater":null},{"KandidatlisteId":"57b064d3-da23-45c7-bf15-c5765157bebd","Navn":"SF - Socialistisk Folkeparti","Bogstavbetegnelse":"F","Stemmer":257,"Listestemmer":null,"StemmerDifferenceFraForrigeValg":114,"Kandidater":null},{"KandidatlisteId":"a653c687-4e33-46c3-a22f-c794846f2994","Navn":"Liberal Alliance","Bogstavbetegnelse":"I","Stemmer":60,"Listestemmer":null,"StemmerDifferenceFraForrigeValg":41,"Kandidater":null},{"KandidatlisteId":"9cab9f7c-3ea7-427a-bf33-12ddc90b2dea","Navn":"Kristendemokraterne","Bogstavbetegnelse":"K","Stemmer":13,"Listestemmer":null,"StemmerDifferenceFraForrigeValg":null,"Kandidater":null},{"KandidatlisteId":"b522e809-c0b8-4802-b94a-953cb8d86694","Navn":"Dansk Folkeparti","Bogstavbetegnelse":"O","Stemmer":350,"Listestemmer":null,"StemmerDifferenceFraForrigeValg":235,"Kandidater":null},{"KandidatlisteId":"38731762-e300-400c-b3e4-d31760dccc4d","Navn":"Enhedslisten - De Rød-Grønne","Bogstavbetegnelse":"Ø","Stemmer":180,"Listestemmer":null,"StemmerDifferenceFraForrigeValg":56,"Kandidater":null},{"KandidatlisteId":"7e1e07c7-be39-4e07-a7c8-662fa901dc12","Navn":"Radikale Venstre","Bogstavbetegnelse":"B","Stemmer":56,"Listestemmer":null,"StemmerDifferenceFraForrigeValg":12,"Kandidater":null},{"KandidatlisteId":"acb0f894-58a7-406c-9cfe-f65a88808308","Navn":"Venstre, Danmarks Liberale Parti","Bogstavbetegnelse":"V","Stemmer":79,"Listestemmer":null,"StemmerDifferenceFraForrigeValg":-53,"Kandidater":null}],"GodkendelsesDatoUTC":"18-11-2025 21:42:02","Valgdag":"18-11-2025","Valgart":"Kommunalvalg","FrigivelsesTidspunktUTC":"18-11-2025 22:14:34","Storkreds":null,"Storkredsnummer":null,"Opstillingskreds":null,"OpstillingskredsDagiId":null,"Kommune":"Brøndby","Kommunekode":153,"AfstemningsområdeNummer":3,"AfstemningsområdeDagiId":708674,"Afstemningsområde":"Lindelundshallen","UgyldigeFremmødteStemmerÅrsager":[{"Id":3,"Navn":"HeltEllerDelvistOverstreget","Paragraf":"6","Antal":0},{"Id":4,"Navn":"KrydsUdenForFelterne","Paragraf":"7","Antal":1},{"Id":6,"Navn":"KrydsRækkerIndIflereFelter","Paragraf":"9,10","Antal":2},{"Id":12,"Navn":"StemmeseddelMedTegningPåskrift","Paragraf":"16","Antal":0},{"Id":10,"Navn":"AndetMærkeEndKrydsForudenKryds","Paragraf":"14","Antal":0},{"Id":9,"Navn":"StemmeseddelIkkeUdFraAfstemningssted","Paragraf":"13","Antal":0},{"Id":13,"Navn":"AfmærketMedForskelligeFarverOgAndet","Paragraf":"17","Antal":0},{"Id":7,"Navn":"OverstregetUdvisketEllerIkkeFuldtKryds","Paragraf":"11","Antal":0},{"Id":11,"Navn":"AnførtFlereEndTreKryds","Paragraf":"15","Antal":0},{"Id":8,"Navn":"AndreGrunde","Paragraf":"12","Antal":0},{"Id":2,"Navn":"AndetMærkeEndKryds","Paragraf":"5","Antal":0},{"Id":5,"Navn":"KrydsIflereFelter","Paragraf":"8","Antal":5},{"Id":1,"Navn":"Blanke","Paragraf":"4","Antal":43}],"UgyldigeBrevstemmerÅrsager":[{"Id":21,"Navn":"Blanke","Paragraf":"19","Antal":3},{"Id":26,"Navn":"ModstridBogstavListeNavn","Paragraf":"24, 25","Antal":10},{"Id":24,"Navn":"KunUofficelBogstavPåFlereBogstaver","Paragraf":"22","Antal":1},{"Id":32,"Navn":"UdfyldtPåBagsidenEllerAndet","Paragraf":"31","Antal":0},{"Id":30,"Navn":"KonvolutMedPåskrift","Paragraf":"29","Antal":0},{"Id":27,"Navn":"AndreGrunde","Paragraf":"26","Antal":0},{"Id":29,"Navn":"StemmeseddelIkkeFraMinisteren","Paragraf":"28","Antal":0},{"Id":31,"Navn":"StemmeseddelMedTegningPåskrift","Paragraf":"30","Antal":0},{"Id":28,"Navn":"AndetEllerMereEndEnStemmeseddel","Paragraf":"27","Antal":0},{"Id":23,"Navn":"KunUofficelBogstavPåEtBogstav","Paragraf":"21","Antal":0},{"Id":25,"Navn":"KunKryds","Paragraf":"23","Antal":0},{"Id":22,"Navn":"KunNavnUofficielBogstav","Paragraf":"20","Antal":1}],"Resultatart":"ForeløbigOptælling","AfgivneStemmer":2215,"GyldigeStemmer":2149,"UgyldigeStemmerUdoverBlanke":20,"BlankeUgyldigeFremmødteStemmer":43,"BlankeUgyldigeBrevstemmer":3,"AfgivneStemmerDifferenceFraForrigeValg":174,"GyldigeStemmerDifferenceFraForrigeValg":156,"UgyldigeStemmerDifferenceFraForrigeValg":12,"BlankeStemmerDifferenceFraForrigeValg":6,"AntalStemmeberettigedeVælgereDifferenceFraForrigeValg":311,"AntalStemmeberettigedeVælgere":3673}