{"Valgart":"Kommunal- og regionsrådsvalg","Valgdag":"18-11-2025","FrigivelsesTidspunktUTC":"18-11-2025 17:04:11","Kommune":"Haderslev","Kommunekode":510,"Afstemningsområde":"Haderslev Syd","AfstemningsområdeDagiId":"707626","AfstemningsområdeNummer":2,"Valgdeltagelse":[{"AntalStemmeberretigedeVælgere":5509,"AfgivneStemmer":1021,"Tidspunkt":"11:00:00"},{"AntalStemmeberretigedeVælgere":5509,"AfgivneStemmer":1044,"Tidspunkt":"11:11:00"},{"AntalStemmeberretigedeVælgere":5509,"AfgivneStemmer":1821,"Tidspunkt":"14:50:00"},{"AntalStemmeberretigedeVælgere":5509,"AfgivneStemmer":1833,"Tidspunkt":"15:00:00"},{"AntalStemmeberretigedeVælgere":5509,"AfgivneStemmer":3085,"Tidspunkt":"17:58:00"}]}