{"Valgart":"Kommunal- og regionsrådsvalg","Valgdag":"18-11-2025","FrigivelsesTidspunktUTC":"18-11-2025 17:21:57","Kommune":"Tønder","Kommunekode":550,"Afstemningsområde":"Branderup","AfstemningsområdeDagiId":"709622","AfstemningsområdeNummer":19,"Valgdeltagelse":[{"AntalStemmeberretigedeVælgere":392,"AfgivneStemmer":22,"Tidspunkt":"09:00:00"},{"AntalStemmeberretigedeVælgere":392,"AfgivneStemmer":74,"Tidspunkt":"12:00:00"},{"AntalStemmeberretigedeVælgere":392,"AfgivneStemmer":121,"Tidspunkt":"15:00:00"},{"AntalStemmeberretigedeVælgere":392,"AfgivneStemmer":209,"Tidspunkt":"18:00:00"}]}