{"Valgart":"Kommunal- og regionsrådsvalg","Valgdag":"18-11-2025","FrigivelsesTidspunktUTC":"18-11-2025 18:13:01","Kommune":"Vordingborg","Kommunekode":390,"Afstemningsområde":"Vestmøn","AfstemningsområdeDagiId":"701698","AfstemningsområdeNummer":10,"Valgdeltagelse":[{"AntalStemmeberretigedeVælgere":1788,"AfgivneStemmer":238,"Tidspunkt":"10:00:00"},{"AntalStemmeberretigedeVælgere":1788,"AfgivneStemmer":344,"Tidspunkt":"11:00:00"},{"AntalStemmeberretigedeVælgere":1788,"AfgivneStemmer":444,"Tidspunkt":"12:00:00"},{"AntalStemmeberretigedeVælgere":1788,"AfgivneStemmer":522,"Tidspunkt":"13:00:00"},{"AntalStemmeberretigedeVælgere":1788,"AfgivneStemmer":622,"Tidspunkt":"14:05:00"},{"AntalStemmeberretigedeVælgere":1788,"AfgivneStemmer":716,"Tidspunkt":"15:05:00"},{"AntalStemmeberretigedeVælgere":1788,"AfgivneStemmer":829,"Tidspunkt":"16:00:00"},{"AntalStemmeberretigedeVælgere":1788,"AfgivneStemmer":1010,"Tidspunkt":"17:00:00"},{"AntalStemmeberretigedeVælgere":1788,"AfgivneStemmer":1066,"Tidspunkt":"18:00:00"},{"AntalStemmeberretigedeVælgere":1788,"AfgivneStemmer":1278,"Tidspunkt":"19:00:00"}]}