{"Valgart":"Kommunal- og regionsrådsvalg","Valgdag":"18-11-2025","FrigivelsesTidspunktUTC":"18-11-2025 15:00:58","Kommune":"Silkeborg","Kommunekode":740,"Afstemningsområde":"Kjellerup","AfstemningsområdeDagiId":"711260","AfstemningsområdeNummer":7,"Valgdeltagelse":[{"AntalStemmeberretigedeVælgere":4721,"AfgivneStemmer":808,"Tidspunkt":"11:00:00"},{"AntalStemmeberretigedeVælgere":4721,"AfgivneStemmer":1226,"Tidspunkt":"13:00:00"},{"AntalStemmeberretigedeVælgere":4721,"AfgivneStemmer":1556,"Tidspunkt":"16:00:00"}]}