{"Kommune":"Solrød","KommuneDagiId":"389138","Valgforbund":[{"ValgforbundId":"10994345-1e3b-4b61-9641-b7aff3683a7f","Navn":"Valgforbund 1","KandidatlisteId":["8c868337-e49f-4680-a507-4abd1acafc0e","e79b7178-9abb-419f-9198-423dcdd17add","f74d1e6c-2ca0-458a-831a-a08877ca809b"]},{"ValgforbundId":"6462ba2f-8dbb-40f7-b56f-37faf506cb83","Navn":"Valgforbund 3","KandidatlisteId":["602da47f-e43a-4ac4-9622-dcf7b34e0cd8","6558e386-cb78-47dc-a893-4d0720d4ad1b","d5e7ca49-ca73-4757-ab66-28d7ff459169"]},{"ValgforbundId":"c7c10b9e-4597-432f-a22c-efb4ffa363d8","Navn":"Valgforbund 2","KandidatlisteId":["3f50d8ee-d33a-4f3b-80f2-d0d2a500b3f9","8601320b-5524-4d60-81e4-ebe37484b021","f1017b16-3be1-4656-a6da-032b3d2e1342"]}],"Kandidatlister":[{"KandidatlisteId":"f8dcf573-aa72-491d-a72f-ac96e4a8aa8f","Stemmeseddelsplacering":1,"Bogstavbetegnelse":"A","Navn":"Socialdemokratiet","Opstillingsform":"Sideordnet","Kandidater":[{"Stemmeseddelsplacering":1,"Id":"43cc94de-cd77-404f-b20c-427634eaf7e5","Navn":"Jonas Ring Madsen","Stemmeseddelnavn":"Jonas Ring Madsen","Stilling":"Konsulent","BopaelPaaStemmeseddel":""},{"Stemmeseddelsplacering":2,"Id":"29b37b38-225a-413c-8f77-f569de7ca45d","Navn":"Hanne Bache Vognbjerg","Stemmeseddelnavn":"Hanne Bache Vognbjerg","Stilling":"Konsulent","BopaelPaaStemmeseddel":""},{"Stemmeseddelsplacering":3,"Id":"66e0668d-87f9-428d-89f5-c8d7e5e617e4","Navn":"Nicklas Gregil","Stemmeseddelnavn":"Nicklas Gregil","Stilling":"Førtidspensionist","BopaelPaaStemmeseddel":""},{"Stemmeseddelsplacering":4,"Id":"17e71c80-f126-49db-b5a8-8e54b42d3966","Navn":"Jytte Willendrup","Stemmeseddelnavn":"Jytte Willendrup","Stilling":"Efterlønsmodtager","BopaelPaaStemmeseddel":""},{"Stemmeseddelsplacering":5,"Id":"1a2d44e1-4854-41b2-8ef9-47794ac62472","Navn":"Finn Larsen","Stemmeseddelnavn":"Finn Larsen","Stilling":"Seniorkonsulent","BopaelPaaStemmeseddel":""},{"Stemmeseddelsplacering":6,"Id":"53c056e2-4dac-449f-bea0-ba24041db9ee","Navn":"John Løvenskjold Nielsen","Stemmeseddelnavn":"John Løvenskjold Nielsen","Stilling":"Trafikoperatør","BopaelPaaStemmeseddel":""}]},{"KandidatlisteId":"e79b7178-9abb-419f-9198-423dcdd17add","Stemmeseddelsplacering":2,"Bogstavbetegnelse":"B","Navn":"Radikale Venstre","Opstillingsform":"Sideordnet","Kandidater":[{"Stemmeseddelsplacering":1,"Id":"3dd5f4f5-f4df-4c6c-a65e-791966599caa","Navn":"Per Laursen","Stemmeseddelnavn":"Per Laursen","Stilling":"IT-ingeniør","BopaelPaaStemmeseddel":""},{"Stemmeseddelsplacering":2,"Id":"128947d8-7fc9-4f84-bf3a-fdf08c637c58","Navn":"Kim Pagels","Stemmeseddelnavn":"Kim Pagels","Stilling":"Juridisk konsulent","BopaelPaaStemmeseddel":""},{"Stemmeseddelsplacering":3,"Id":"9c6896f1-5bc7-45ba-83b4-0fff144d426d","Navn":"Marius Buch Holtze","Stemmeseddelnavn":"Marius Holtze","Stilling":"Gymnasieelev","BopaelPaaStemmeseddel":""},{"Stemmeseddelsplacering":4,"Id":"4d8f3db2-bfbb-40f8-aea3-497ea5bc80bb","Navn":"Kenneth Øverup","Stemmeseddelnavn":"Kenneth Øverup","Stilling":"Pædagogisk assistent","BopaelPaaStemmeseddel":""}]},{"KandidatlisteId":"3f50d8ee-d33a-4f3b-80f2-d0d2a500b3f9","Stemmeseddelsplacering":3,"Bogstavbetegnelse":"C","Navn":"Det Konservative Folkeparti","Opstillingsform":"Sideordnet","Kandidater":[{"Stemmeseddelsplacering":1,"Id":"238a01df-1585-488f-9d1b-5909b48b01d4","Navn":"Morten Peder Scheelsbeck","Stemmeseddelnavn":"Morten Scheelsbeck, Solrød Strand","Stilling":"Journalist","BopaelPaaStemmeseddel":"Solrød Strand"},{"Stemmeseddelsplacering":2,"Id":"297e6bd0-238d-4737-bebd-16acb36e5914","Navn":"Jan Færch","Stemmeseddelnavn":"Jan Færch, Solrød Strand","Stilling":"CEO","BopaelPaaStemmeseddel":"Solrød Strand"},{"Stemmeseddelsplacering":3,"Id":"c8dfb85a-fb21-442f-bc66-761159028a9d","Navn":"Mads Silberg Niebuhr","Stemmeseddelnavn":"Mads Silberg, Solrød Strand","Stilling":"Team leder","BopaelPaaStemmeseddel":"Solrød Strand"},{"Stemmeseddelsplacering":4,"Id":"c3e1cc13-bb39-46c4-b02a-218c8d528f7a","Navn":"Mads Ramstedt","Stemmeseddelnavn":"Mads Ramstedt, Jersie Strand","Stilling":"Studerende","BopaelPaaStemmeseddel":"Jersie Strand"},{"Stemmeseddelsplacering":5,"Id":"d3ce1bc1-d971-449f-89bf-0d07a298e861","Navn":"Therese Færch Nebel","Stemmeseddelnavn":"Therese Færch Nebel, Solrød Strand","Stilling":"Social- og sundhedsassistent","BopaelPaaStemmeseddel":"Solrød Strand"},{"Stemmeseddelsplacering":6,"Id":"c1164770-3e6f-4add-99ba-c9c966fd727b","Navn":"John Mogensen","Stemmeseddelnavn":"John Mogensen, Havdrup","Stilling":"Direktør","BopaelPaaStemmeseddel":"Havdrup"},{"Stemmeseddelsplacering":7,"Id":"2df28325-e53c-4ef8-8f5c-6c54c92ce099","Navn":"Jørgen Kauling","Stemmeseddelnavn":"Jørgen Kauling, Havdrup","Stilling":"Pensionist","BopaelPaaStemmeseddel":"Havdrup"},{"Stemmeseddelsplacering":8,"Id":"948b799f-327a-42f2-b0b7-d821a307b71e","Navn":"Mia Qvist Scheelsbeck","Stemmeseddelnavn":"Mia Qvist Scheelsbeck, Solrød Strand","Stilling":"Kommunikationskonsulent","BopaelPaaStemmeseddel":"Solrød Strand"},{"Stemmeseddelsplacering":9,"Id":"956f43c2-ded1-448e-918b-3d967639d3b6","Navn":"Lene Fly","Stemmeseddelnavn":"Lene Fly, Solrød Strand","Stilling":"Chefkonsulent","BopaelPaaStemmeseddel":"Solrød Strand"},{"Stemmeseddelsplacering":10,"Id":"cbfa3bcb-274d-4bbb-8297-9836dfe38116","Navn":"Kim Piasecki Hansen","Stemmeseddelnavn":"Kim P. Hansen, Solrød Strand","Stilling":"Politibetjent / -assistent","BopaelPaaStemmeseddel":"Solrød Strand"}]},{"KandidatlisteId":"8c868337-e49f-4680-a507-4abd1acafc0e","Stemmeseddelsplacering":4,"Bogstavbetegnelse":"F","Navn":"SF - Socialistisk Folkeparti","Opstillingsform":"Partiliste","Kandidater":[{"Stemmeseddelsplacering":1,"Id":"488038c4-1b51-4065-9caa-3f3f198e9733","Navn":"Claus Redder Madsen","Stemmeseddelnavn":"Claus Redder Madsen, Jersie","Stilling":"Politibetjent / -assistent","BopaelPaaStemmeseddel":"Jersie"},{"Stemmeseddelsplacering":2,"Id":"aa7d2dc9-5a2e-4ab7-b487-24d8be3c5eb3","Navn":"Farid Faizi","Stemmeseddelnavn":"Farid Faizi, Solrød Strand","Stilling":"Social- og sundhedsassistent","BopaelPaaStemmeseddel":"Solrød Strand"},{"Stemmeseddelsplacering":3,"Id":"aeca2842-d349-4c66-8dad-f586f6f97222","Navn":"Marianne Sonja Lejbølle Svane","Stemmeseddelnavn":"Marianne Svane, Jersie Strand","Stilling":"Skoleleder","BopaelPaaStemmeseddel":"Jersie Strand"}]},{"KandidatlisteId":"a8ec0fef-abd8-4b3c-95e5-c7ac52fa1ee3","Stemmeseddelsplacering":5,"Bogstavbetegnelse":"I","Navn":"Liberal Alliance","Opstillingsform":"Sideordnet","Kandidater":[{"Stemmeseddelsplacering":1,"Id":"025ae59d-520d-45b2-a04b-ab072e95f4e8","Navn":"Emil Blücher","Stemmeseddelnavn":"Emil Blücher, Jersie Strand","Stilling":"Iværksætter","BopaelPaaStemmeseddel":"Jersie Strand"},{"Stemmeseddelsplacering":2,"Id":"3dabb5d8-af20-4ba5-b73a-3d647aeff038","Navn":"Regine Hjort Hovmøller","Stemmeseddelnavn":"Regine Hovmøller, Jersie Strand","Stilling":"Folkeskolelærer","BopaelPaaStemmeseddel":"Jersie Strand"},{"Stemmeseddelsplacering":3,"Id":"00b4e964-63e5-4a87-9df9-7f593f9fa488","Navn":"Carl Andersen","Stemmeseddelnavn":"Carl Andersen, Havdrup","Stilling":"Jordbrugsøkonom","BopaelPaaStemmeseddel":"Havdrup"},{"Stemmeseddelsplacering":4,"Id":"f1d2e99a-2a8b-4f78-b48c-998a65b05cf5","Navn":"Flemming Warhøi-Rasmussen","Stemmeseddelnavn":"Flemming Warhøi, Solrød Strand","Stilling":"Finanschef","BopaelPaaStemmeseddel":"Solrød Strand"},{"Stemmeseddelsplacering":5,"Id":"25c4a457-e80c-4d00-915b-e92e297c0c5e","Navn":"Henrik Boye","Stemmeseddelnavn":"Henrik Boye, Solrød Strand","Stilling":"HR manager","BopaelPaaStemmeseddel":"Solrød Strand"},{"Stemmeseddelsplacering":6,"Id":"7c80ca7f-b25c-49b7-9922-97e55d6b6d91","Navn":"Pernille Breinholdt Jepsen","Stemmeseddelnavn":"Pernille Breinholdt Jepsen, Jersie Strand","Stilling":"Pædagog","BopaelPaaStemmeseddel":"Jersie Strand"},{"Stemmeseddelsplacering":7,"Id":"357e7706-f246-479d-aaa9-8494cd1b4842","Navn":"Peter Dits Christensen","Stemmeseddelnavn":"Peter Dits Christensen, Trylleskoven Strand","Stilling":"Social- og sundhedsassistent","BopaelPaaStemmeseddel":"Trylleskoven Strand"},{"Stemmeseddelsplacering":8,"Id":"01cf8ede-411c-400b-8ba6-bfdb930aa662","Navn":"Ulrik Nick Lassen","Stemmeseddelnavn":"Ulrik Lassen, Jersie Strand","Stilling":"Bestyrer","BopaelPaaStemmeseddel":"Jersie Strand"},{"Stemmeseddelsplacering":9,"Id":"916dc11d-0ff4-4ca6-b698-553985a13701","Navn":"Nils Lagoni","Stemmeseddelnavn":"Nils Lagoni, Solrød Landsby","Stilling":"Leder","BopaelPaaStemmeseddel":"Solrød Landsby"},{"Stemmeseddelsplacering":10,"Id":"e9822758-1378-47e1-b686-0242ce3279f3","Navn":"Arthur Roberti Kosakian","Stemmeseddelnavn":"Arthur Roberti Kosakian, Gl. Havdrup","Stilling":"Økonomiansvarlig","BopaelPaaStemmeseddel":"Gl. Havdrup"},{"Stemmeseddelsplacering":11,"Id":"6c0e5374-31d8-43d8-b321-1664824d1680","Navn":"Daniel Bidstrup Nielsen","Stemmeseddelnavn":"Daniel Bidstrup Nielsen, Jersie Landsby","Stilling":"Operatør","BopaelPaaStemmeseddel":"Jersie Landsby"},{"Stemmeseddelsplacering":12,"Id":"018870d4-f766-4cda-b0f2-4815a567abcc","Navn":"Peter Flemming Teunissen Sjølin","Stemmeseddelnavn":"Peter Sjølin, Jersie Strand","Stilling":"Cand.IT","BopaelPaaStemmeseddel":"Jersie Strand"},{"Stemmeseddelsplacering":13,"Id":"f8b5b2ec-4237-4593-9ca6-8fb011bd9f1c","Navn":"Nikolaj Brink Olsen","Stemmeseddelnavn":"Nikolaj Brink Olsen, Havdrup","Stilling":"Salgsspecialist","BopaelPaaStemmeseddel":"Havdrup"},{"Stemmeseddelsplacering":14,"Id":"16b94ad4-833a-4ae5-9f99-4247cf10e8a7","Navn":"Linda Vestergaard Møller","Stemmeseddelnavn":"Linda Vestergaard Møller, Karlstrup Strand","Stilling":"Advokat","BopaelPaaStemmeseddel":"Karlstrup Strand"}]},{"KandidatlisteId":"f1017b16-3be1-4656-a6da-032b3d2e1342","Stemmeseddelsplacering":6,"Bogstavbetegnelse":"L","Navn":"HavdrupListen","Opstillingsform":"Partiliste","Kandidater":[{"Stemmeseddelsplacering":1,"Id":"835942a3-8ef3-4ebf-b88f-2a47b90caf53","Navn":"Bo Christoph Christiansen","Stemmeseddelnavn":"Bo C. Christiansen, Havdrup","Stilling":"Seniorspecialist","BopaelPaaStemmeseddel":"Havdrup"},{"Stemmeseddelsplacering":2,"Id":"e2065f32-eca7-4123-8140-84510c4ea88e","Navn":"Christian Vang","Stemmeseddelnavn":"Christian Vang, Havdrup","Stilling":"Markedschef","BopaelPaaStemmeseddel":"Havdrup"},{"Stemmeseddelsplacering":3,"Id":"0a3f2e03-e219-43ce-83b2-15d169fcb7d8","Navn":"Stine Ulfkjær Johansen","Stemmeseddelnavn":"Stine U. Johansen, Havdrup","Stilling":"Teamleder","BopaelPaaStemmeseddel":"Havdrup"},{"Stemmeseddelsplacering":4,"Id":"a798acda-4a78-48b0-ad5d-bf19c3c60cbf","Navn":"Lars Møller Christiansen","Stemmeseddelnavn":"Lars Møller Christiansen, Havdrup","Stilling":"Økonomidirektør","BopaelPaaStemmeseddel":"Havdrup"},{"Stemmeseddelsplacering":5,"Id":"e938d415-b962-460f-9bea-75db62e65cc8","Navn":"Ina Lindemark","Stemmeseddelnavn":"Ina Lindemark, Jersie Landsby","Stilling":"Landmand","BopaelPaaStemmeseddel":"Jersie Landsby"},{"Stemmeseddelsplacering":6,"Id":"84315c73-d629-4732-b876-a0c6154b0e18","Navn":"Finn Harald Holm Jensen","Stemmeseddelnavn":"Finn Jensen, Havdrup","Stilling":"Revisor","BopaelPaaStemmeseddel":"Havdrup"}]},{"KandidatlisteId":"6558e386-cb78-47dc-a893-4d0720d4ad1b","Stemmeseddelsplacering":7,"Bogstavbetegnelse":"O","Navn":"Dansk Folkeparti","Opstillingsform":"Partiliste","Kandidater":[{"Stemmeseddelsplacering":1,"Id":"457b41fc-8633-4822-8f7f-f7994c491cd1","Navn":"Nico Sandager Hjermind","Stemmeseddelnavn":"Nico Hjermind","Stilling":"Lærer","BopaelPaaStemmeseddel":""}]},{"KandidatlisteId":"8601320b-5524-4d60-81e4-ebe37484b021","Stemmeseddelsplacering":8,"Bogstavbetegnelse":"T","Navn":"VoresSolrød","Opstillingsform":"Sideordnet","Kandidater":[{"Stemmeseddelsplacering":1,"Id":"e44cd9d5-cd72-4ff0-bdcf-d6f9485232eb","Navn":"Anette Fynbo Blem","Stemmeseddelnavn":"Anette Fynbo Blem","Stilling":"Uddannelsesvejleder","BopaelPaaStemmeseddel":""},{"Stemmeseddelsplacering":2,"Id":"c1ed2b33-c5a8-4241-ac8d-b122cbee60a1","Navn":"Lil Bekker Lyrstrand","Stemmeseddelnavn":"Lil Lyrstrand","Stilling":"Underviser","BopaelPaaStemmeseddel":""},{"Stemmeseddelsplacering":3,"Id":"7b593037-ab85-444d-aa8e-8d466b33100c","Navn":"Anne Kirstine Raun Senderovitz","Stemmeseddelnavn":"Anne Kirstine Raun Senderovitz","Stilling":"Strategisk rådgiver","BopaelPaaStemmeseddel":""},{"Stemmeseddelsplacering":4,"Id":"49c4b836-52c3-4430-a4d0-71aa0837350e","Navn":"Jannik Skriver Jensen","Stemmeseddelnavn":"Jannik Jensen","Stilling":"Business development manager","BopaelPaaStemmeseddel":""},{"Stemmeseddelsplacering":5,"Id":"429b899c-140c-4f0c-8069-8582e80a5414","Navn":"Knud Rasmussen","Stemmeseddelnavn":"Knud Rasmussen","Stilling":"Produktspecialist","BopaelPaaStemmeseddel":""},{"Stemmeseddelsplacering":6,"Id":"e449c8a3-1705-4528-9141-3e454245b8c5","Navn":"Per Schmidt Jensen","Stemmeseddelnavn":"Per Schmidt Jensen","Stilling":"Kørselsleder","BopaelPaaStemmeseddel":""},{"Stemmeseddelsplacering":7,"Id":"8a65f8b0-c37b-4edf-b37c-58b208ca2b39","Navn":"Jeppe Hagenbæk Sørensen","Stemmeseddelnavn":"Jeppe Hagenbæk Sørensen","Stilling":"Chefkonsulent","BopaelPaaStemmeseddel":""}]},{"KandidatlisteId":"d5e7ca49-ca73-4757-ab66-28d7ff459169","Stemmeseddelsplacering":9,"Bogstavbetegnelse":"V","Navn":"Venstre, Danmarks Liberale Parti","Opstillingsform":"Sideordnet","Kandidater":[{"Stemmeseddelsplacering":1,"Id":"665e2d13-4906-4280-a161-f9ca41402d7b","Navn":"Kim Kliver","Stemmeseddelnavn":"Kim Kliver, Havdrup","Stilling":"Politiinspektør","BopaelPaaStemmeseddel":"Havdrup"},{"Stemmeseddelsplacering":2,"Id":"04378f3f-ada4-403a-b3a6-5fed3f890e72","Navn":"Nikolaj Hviid Schwartz","Stemmeseddelnavn":"Nikolaj Schwartz, Solrød Strand","Stilling":"Direktør","BopaelPaaStemmeseddel":"Solrød Strand"},{"Stemmeseddelsplacering":3,"Id":"d208d997-fb00-4e43-82b2-8945be0ec66e","Navn":"Niels Emil Haulund Hörup","Stemmeseddelnavn":"Niels Hörup, Solrød Strand","Stilling":"Direktør","BopaelPaaStemmeseddel":"Solrød Strand"},{"Stemmeseddelsplacering":4,"Id":"a0626b93-78fa-4676-a276-9ea11264ef41","Navn":"Lene Mølbak","Stemmeseddelnavn":"Lene Mølbak, Jersie Strand","Stilling":"Sygeplejerske","BopaelPaaStemmeseddel":"Jersie Strand"},{"Stemmeseddelsplacering":5,"Id":"1c42b0e3-cd0a-4d4e-be44-f94791cd38fb","Navn":"Musa Akin","Stemmeseddelnavn":"Musa Akin, Jersie Strand","Stilling":"Restauratør","BopaelPaaStemmeseddel":"Jersie Strand"},{"Stemmeseddelsplacering":6,"Id":"f5fb8a1a-3f3a-461a-8e7b-e1057f68101e","Navn":"Per Gunnar Dahlin","Stemmeseddelnavn":"Per Dahlin, Solrød Strand","Stilling":"Driftschef","BopaelPaaStemmeseddel":"Solrød Strand"},{"Stemmeseddelsplacering":7,"Id":"16a67483-0e65-4252-9eae-21860aebf41d","Navn":"Alan Jakob Wagner Kampman","Stemmeseddelnavn":"Alan Kampman, Solrød Strand","Stilling":"Operationel supervisor","BopaelPaaStemmeseddel":"Solrød Strand"},{"Stemmeseddelsplacering":8,"Id":"318dc5d3-196a-4443-bece-5798776c2835","Navn":"Henning Madsen","Stemmeseddelnavn":"Henning Madsen, Gl. Havdrup","Stilling":"Landmand","BopaelPaaStemmeseddel":"Gl. Havdrup"},{"Stemmeseddelsplacering":9,"Id":"b6884fcb-1647-435f-940a-ef79b7bd53c6","Navn":"Stig Hoffmann Johansen","Stemmeseddelnavn":"Stig Johansen, Havdrup","Stilling":"Ingeniør","BopaelPaaStemmeseddel":"Havdrup"},{"Stemmeseddelsplacering":10,"Id":"a31904a6-028d-46dd-ae9c-a19306395113","Navn":"Dina Esther Oxfeldt Grøn-Norup","Stemmeseddelnavn":"Dina Oxfeldt, Jersie Strand","Stilling":"Fuldmægtig","BopaelPaaStemmeseddel":"Jersie Strand"},{"Stemmeseddelsplacering":11,"Id":"4458b77f-2b67-47c8-a641-938e254ec270","Navn":"Louise Irgens Skov","Stemmeseddelnavn":"Louise Irgens, Solrød Strand","Stilling":"Kategorigruppechef","BopaelPaaStemmeseddel":"Solrød Strand"},{"Stemmeseddelsplacering":12,"Id":"63bd8613-3f56-48dc-857e-ecbd2aa73e76","Navn":"Frank Ellegaard Nielsen","Stemmeseddelnavn":"Frank Ellegaard Nielsen, Solrød Strand","Stilling":"A-kasse rådgiver","BopaelPaaStemmeseddel":"Solrød Strand"}]},{"KandidatlisteId":"602da47f-e43a-4ac4-9622-dcf7b34e0cd8","Stemmeseddelsplacering":10,"Bogstavbetegnelse":"Æ","Navn":"Danmarksdemokraterne - Inger Støjberg","Opstillingsform":"Sideordnet","Kandidater":[{"Stemmeseddelsplacering":1,"Id":"cbf8d55f-e510-4516-9f5d-cd8648763643","Navn":"Brian Mørch","Stemmeseddelnavn":"Brian Mørch","Stilling":"Sagsbehandler","BopaelPaaStemmeseddel":""},{"Stemmeseddelsplacering":2,"Id":"c450af2c-9260-4230-b074-0ed91ef96aeb","Navn":"Emil Carl Kirketerp Hansen","Stemmeseddelnavn":"Emil Kirketerp Hansen","Stilling":"Studerende","BopaelPaaStemmeseddel":""},{"Stemmeseddelsplacering":3,"Id":"39bd4653-92b2-414f-84da-a818fcf4ea27","Navn":"Michael Folmann Jensen","Stemmeseddelnavn":"Michael Folmann Jensen","Stilling":"Selvstændig","BopaelPaaStemmeseddel":""},{"Stemmeseddelsplacering":4,"Id":"e880f839-f6bb-41a7-9eb3-9be7ebec93c5","Navn":"Lotte Rojen Hansen","Stemmeseddelnavn":"Lotte Rojen Hansen","Stilling":"Hjemmehjælper","BopaelPaaStemmeseddel":""},{"Stemmeseddelsplacering":5,"Id":"6bb07881-0dce-48b0-ab93-915a41e256e1","Navn":"Jens Jørgen Fiskbæk","Stemmeseddelnavn":"Jens Fiskbæk","Stilling":"Pensionist","BopaelPaaStemmeseddel":""},{"Stemmeseddelsplacering":6,"Id":"b3ea3e6c-e37f-45be-88c0-db1159e67d81","Navn":"Lubima Jensen","Stemmeseddelnavn":"Lubima Jensen","Stilling":"Idrætsinstruktør","BopaelPaaStemmeseddel":""},{"Stemmeseddelsplacering":7,"Id":"0d7e53e4-917a-4b60-9c2a-af60758b3950","Navn":"Per Pohlmann","Stemmeseddelnavn":"Per Pohlmann","Stilling":"Elev","BopaelPaaStemmeseddel":""},{"Stemmeseddelsplacering":8,"Id":"47ca6976-e5c9-4b84-8ce7-aa25a823665b","Navn":"Knud Vagn Steffen Røgind","Stemmeseddelnavn":"Steffen Røgind","Stilling":"Håndværker","BopaelPaaStemmeseddel":""},{"Stemmeseddelsplacering":9,"Id":"54b9d893-fc78-4a8f-ba0d-6c14102a11af","Navn":"Joan Bente Forup","Stemmeseddelnavn":"Joan Forup","Stilling":"Pensionist","BopaelPaaStemmeseddel":""},{"Stemmeseddelsplacering":10,"Id":"c89dd9fa-3896-4263-8af6-286652ecaef6","Navn":"Tommy Winther","Stemmeseddelnavn":"Tommy Winther","Stilling":"Litograf","BopaelPaaStemmeseddel":""},{"Stemmeseddelsplacering":11,"Id":"27cd2bf4-f385-4f30-9c9c-964b2a29660a","Navn":"Flemming Kirketerp Hansen","Stemmeseddelnavn":"Flemming Kirketerp Hansen","Stilling":"Lærer","BopaelPaaStemmeseddel":""}]},{"KandidatlisteId":"f74d1e6c-2ca0-458a-831a-a08877ca809b","Stemmeseddelsplacering":11,"Bogstavbetegnelse":"Ø","Navn":"Enhedslisten - De Rød-Grønne","Opstillingsform":"Partiliste","Kandidater":[{"Stemmeseddelsplacering":1,"Id":"5ecefd01-b302-4cf4-b961-7dabb5725f87","Navn":"Birgit Gedionsen","Stemmeseddelnavn":"Birgit Gedionsen, Gammel Havdrup","Stilling":"Frivillig","BopaelPaaStemmeseddel":"Gammel Havdrup"},{"Stemmeseddelsplacering":2,"Id":"43db15f1-b038-4926-976a-da663acac0eb","Navn":"Karin Østergaard","Stemmeseddelnavn":"Karin Østergaard, Jersie Strand","Stilling":"Pensionist","BopaelPaaStemmeseddel":"Jersie Strand"},{"Stemmeseddelsplacering":3,"Id":"c6aea52b-3330-4a7f-8eee-2152a4e14f76","Navn":"Lola Broe","Stemmeseddelnavn":"Lola Broe, Jersie Strand","Stilling":"Pensionist","BopaelPaaStemmeseddel":"Jersie Strand"}]}],"Valgdag":"18-11-2025","Valgart":"Kommunalvalg","FrigivelsesTidspunktUTC":"06-10-2025 13:07:47","OpdateringsTidspunktUTC":"06-10-2025 13:07:47"}